hazem3010/__init__.py
hazem3010/authintication.py
hazem3010/data.py
hazem3010/email_fake.py
hazem3010/exceptions.py
hazem3010/files.py
hazem3010/five_sim.py
hazem3010/generator.py
hazem3010/input.py
hazem3010/intro.py
hazem3010/mail_tm.py
hazem3010/mediafire.py
hazem3010/phone_numbers.py
hazem3010/premiumy.py
hazem3010/print.py
hazem3010/proxy.py
hazem3010/update.py
hazem3010/urls.py
test/__init__.py
hazem3010-0.1.0.dist-info/METADATA
hazem3010-0.1.0.dist-info/WHEEL
hazem3010-0.1.0.dist-info/top_level.txt
hazem3010-0.1.0.dist-info/RECORD
