Metadata-Version: 2.1
Name: hazem3010
Version: 0.1.0
Requires-Dist: requests ~=2.31.0
Requires-Dist: setuptools ~=65.5.1
Requires-Dist: beautifulsoup4 ~=4.12.2
Requires-Dist: playwright ~=1.40.0
Requires-Dist: names ~=0.3.0
Requires-Dist: phonenumbers ~=8.13.27
Requires-Dist: colorama ~=0.4.6
Requires-Dist: art ~=6.1
